pc_informations/pc_info.py
pc_informations-1.0.6.dist-info/METADATA
pc_informations-1.0.6.dist-info/WHEEL
pc_informations-1.0.6.dist-info/entry_points.txt
pc_informations-1.0.6.dist-info/top_level.txt
pc_informations-1.0.6.dist-info/RECORD
